melhorenvio/__init__.py
melhorenvio/config/__init__.py
melhorenvio/config/config.py
melhorenvio/config/request_options.py
melhorenvio/core/__init__.py
melhorenvio/core/base.py
melhorenvio/http/__init__.py
melhorenvio/http/http_client.py
melhorenvio/resources/__init__.py
melhorenvio/resources/auth.py
melhorenvio/resources/cart.py
melhorenvio/resources/checkout.py
melhorenvio/resources/company.py
melhorenvio/resources/quotation.py
melhorenvio/resources/store.py
melhorenvio/resources/tag.py
melhorenvio/resources/user.py
melhorenvio/sdk.py
melhorenvio-0.1.3.dist-info/LICENSE
melhorenvio-0.1.3.dist-info/METADATA
melhorenvio-0.1.3.dist-info/WHEEL
melhorenvio-0.1.3.dist-info/RECORD
